AUTHORS
LICENSE
MANIFEST.in
README.rst
requirements.txt
setup.py
uvwsgi.py
uvwsgi.egg-info/PKG-INFO
uvwsgi.egg-info/SOURCES.txt
uvwsgi.egg-info/dependency_links.txt
uvwsgi.egg-info/entry_points.txt
uvwsgi.egg-info/not-zip-safe
uvwsgi.egg-info/requires.txt
uvwsgi.egg-info/top_level.txt