Metadata-Version: 1.1
Name: uvwsgi
Version: 0.2.0
Summary: Simple WSGI server using pyuv
Home-page: http://github.com/saghul/uvwsgi
Author: Saúl Ibarra Corretgé
Author-email: saghul@gmail.com
License: UNKNOWN
Platform: POSIX
Platform: Microsoft Windows
Classifier: Development Status :: 4 - Beta
Classifier: Intended Audience :: Developers
Classifier: License :: OSI Approved :: MIT License
Classifier: Operating System :: POSIX
Classifier: Operating System :: Microsoft :: Windows
Classifier: Programming Language :: Python
Classifier: Programming Language :: Python :: 2
Classifier: Programming Language :: Python :: 2.6
Classifier: Programming Language :: Python :: 2.7
Classifier: Programming Language :: Python :: 3
Classifier: Programming Language :: Python :: 3.0
Classifier: Programming Language :: Python :: 3.1
Classifier: Programming Language :: Python :: 3.2
Classifier: Programming Language :: Python :: 3.3
